UsingSwiftWithCocoaAndObjectiveC/README.md
UsingSwiftWithCocoaAndObjectiveC/__init__.py
UsingSwiftWithCocoaAndObjectiveC/__main__.py
UsingSwiftWithCocoaAndObjectiveC/file.epub
UsingSwiftWithCocoaAndObjectiveC/index.html
UsingSwiftWithCocoaAndObjectiveC/css/__init__.py
UsingSwiftWithCocoaAndObjectiveC/css/annotations.css
UsingSwiftWithCocoaAndObjectiveC/css/main.css
UsingSwiftWithCocoaAndObjectiveC/css/normalize.css
UsingSwiftWithCocoaAndObjectiveC/css/popup.css
UsingSwiftWithCocoaAndObjectiveC/font/__init__.py
UsingSwiftWithCocoaAndObjectiveC/font/fontello.eot
UsingSwiftWithCocoaAndObjectiveC/font/fontello.svg
UsingSwiftWithCocoaAndObjectiveC/font/fontello.ttf
UsingSwiftWithCocoaAndObjectiveC/font/fontello.woff
UsingSwiftWithCocoaAndObjectiveC/img/__init__.py
UsingSwiftWithCocoaAndObjectiveC/img/annotator-glyph-sprite.png
UsingSwiftWithCocoaAndObjectiveC/img/annotator-icon-sprite.png
UsingSwiftWithCocoaAndObjectiveC/img/apple-touch-icon.png
UsingSwiftWithCocoaAndObjectiveC/img/cancelfullscreen.png
UsingSwiftWithCocoaAndObjectiveC/img/close.png
UsingSwiftWithCocoaAndObjectiveC/img/fullscreen.png
UsingSwiftWithCocoaAndObjectiveC/img/loader.gif
UsingSwiftWithCocoaAndObjectiveC/img/menu-icon.png
UsingSwiftWithCocoaAndObjectiveC/img/save.png
UsingSwiftWithCocoaAndObjectiveC/img/saved.png
UsingSwiftWithCocoaAndObjectiveC/img/settings-s.png
UsingSwiftWithCocoaAndObjectiveC/img/settings.png
UsingSwiftWithCocoaAndObjectiveC/img/star.png
UsingSwiftWithCocoaAndObjectiveC/js/__init__.py
UsingSwiftWithCocoaAndObjectiveC/js/epub.js
UsingSwiftWithCocoaAndObjectiveC/js/epub.min.js
UsingSwiftWithCocoaAndObjectiveC/js/epub.min.map
UsingSwiftWithCocoaAndObjectiveC/js/hooks.min.js
UsingSwiftWithCocoaAndObjectiveC/js/hooks.min.map
UsingSwiftWithCocoaAndObjectiveC/js/reader.js
UsingSwiftWithCocoaAndObjectiveC/js/reader.js.map
UsingSwiftWithCocoaAndObjectiveC/js/reader.min.js
UsingSwiftWithCocoaAndObjectiveC/js/reader.min.map
UsingSwiftWithCocoaAndObjectiveC/js/hooks/__init__.py
using_swift_with_cocoa_and_objective_c-2024.3.2.0.dist-info/METADATA
using_swift_with_cocoa_and_objective_c-2024.3.2.0.dist-info/WHEEL
using_swift_with_cocoa_and_objective_c-2024.3.2.0.dist-info/entry_points.txt
using_swift_with_cocoa_and_objective_c-2024.3.2.0.dist-info/top_level.txt
using_swift_with_cocoa_and_objective_c-2024.3.2.0.dist-info/RECORD
